Metadata-Version: 2.1
Name: libpython-01
Version: 0.1
Summary: Módulo para exemplificar construção de projetos Python
Home-page: https://github.com/andresousadb/Aprendendo-flake8
Author: André Ferreira
Author-email: andresousadb@gmail.com
License: GNU AFFERO GENERAL PUBLIC LICENSE
Platform: UNKNOWN
Classifier: Development Status :: 2 - Pre-Alpha
Classifier: Environment :: Console
Classifier: Intended Audience :: Developers
Classifier: License :: OSI Approved :: GNU Affero General Public License v3 or later (AGPLv3+)
Classifier: Operating System :: OS Independent
Classifier: Programming Language :: Python
Classifier: Programming Language :: Python :: 3.6
Classifier: Framework :: Pytest
